palettetools/.DS_Store
palettetools/__init__.py
palettetools/constants.py
palettetools/palettetools.py
palettetools/test.py
palettetools-0.8.0.dist-info/METADATA
palettetools-0.8.0.dist-info/RECORD
palettetools-0.8.0.dist-info/WHEEL
palettetools-0.8.0.dist-info/top_level.txt
