Metadata-Version: 2.1
Name: palettetools
Version: 0.8.0
Summary: Color palette tools for processing imgix-served images.
Home-page: https://github.com/sherwinski/palette-tools
Author: sherwinski
Author-email: sherwinhb@gmail.com
License: BSD 2-Clause License
Keywords: image,processing,color,palette,tools,imgix
Platform: UNKNOWN
Classifier: Development Status :: 5 - Production/Stable
Classifier: Intended Audience :: Developers
Classifier: License :: OSI Approved :: BSD License
Classifier: Operating System :: OS Independent
Classifier: Programming Language :: Python
Classifier: Programming Language :: Python :: 2.7
Classifier: Programming Language :: Python :: 3.7
Classifier: Topic :: Utilities
Requires-Dist: requests
